coding_agent/__init__.py
coding_agent/__main__.py
coding_agent/cli.py
coding_agent/config.py
coding_agent/constants.py
coding_agent/functions/call_function.py
coding_agent/functions/get_file_content.py
coding_agent/functions/get_files_info.py
coding_agent/functions/run_python_file.py
coding_agent/functions/write_file.py
coding_agent_python-0.1.0.dist-info/licenses/LICENSE
coding_agent_python-0.1.0.dist-info/METADATA
coding_agent_python-0.1.0.dist-info/WHEEL
coding_agent_python-0.1.0.dist-info/entry_points.txt
coding_agent_python-0.1.0.dist-info/top_level.txt
coding_agent_python-0.1.0.dist-info/RECORD
