Metadata-Version: 2.4
Name: coding-agent-python
Version: 0.1.0
Summary: Add your description here
Author-email: Swikrit Shukla <work.swikrit@gmail.com>
License-Expression: MIT
Requires-Python: >=3.11
License-File: LICENSE
Requires-Dist: google-genai>=1.33.0
Requires-Dist: python-dotenv>=1.1.1
Requires-Dist: streamlit>=1.51.0
Dynamic: license-file
